[
  {
    "date": "09/09/2009",
    "title": "Hana",
    "author": "Yahya",
    "id": 309,
    "name": "Hana",
    "age": "12",
    "type": "Student",
    "classroom": "7"
  },
  {
    "date": "12/12/2012",
    "title": "Around Egypt",
    "author": "Mohamed",
    "id": 96,
    "name": "Yahya",
    "age": "16",
    "type": "Student",
    "classroom": "9"
  },
  {
    "date": "8/8/2008",
    "title": "Around Egypt",
    "author": "Mohamed",
    "id": 273,
    "name": "Mm",
    "age": "66",
    "type": "Teacher",
    "specialization": "Eng"
  }
]